<?xml version="1.0" encoding="utf-8"?>
<search-key-map xmlns="http://www.idpf.org/2007/ops" xml:lang="en">
	<search-key-group href="text/glossary.xhtml#a">
		<match value="a"/>
	</search-key-group>
	<search-key-group href="text/glossary.xhtml#ab">
		<match value="ab"/>
	</search-key-group>
	<search-key-group href="text/glossary.xhtml#ab-on">
		<match value="ab-on"/>
	</search-key-group>
	<search-key-group href="text/glossary.xhtml#ad">
		<match value="ad"/>
	</search-key-group>
	<search-key-group href="text/glossary.xhtml#adad">
		<match value="adad"/>
	</search-key-group>
	<search-key-group href="text/glossary.xhtml#adadad">
		<match value="adadad"/>
	</search-key-group>
	<search-key-group href="text/glossary.xhtml#adaden">
		<match value="adaden"/>
	</search-key-group>
	<search-key-group href="text/glossary.xhtml#aden">
		<match value="aden"/>
	</search-key-group>
	<search-key-group href="text/glossary.xhtml#adenaden">
		<match value="adenaden"/>
	</search-key-group>
	<search-key-group href="text/glossary.xhtml#adenen">
		<match value="adenen"/>
	</search-key-group>
	<search-key-group href="text/glossary.xhtml#a-lur">
		<match value="a-lur"/>
	</search-key-group>
	<search-key-group href="text/glossary.xhtml#an">
		<match value="an"/>
	</search-key-group>
	<search-key-group href="text/glossary.xhtml#an-un">
		<match value="an-un"/>
	</search-key-group>
	<search-key-group href="text/glossary.xhtml#as">
		<match value="as"/>
	</search-key-group>
	<search-key-group href="text/glossary.xhtml#at">
		<match value="at"/>
	</search-key-group>
	<search-key-group href="text/glossary.xhtml#bal">
		<match value="bal"/>
	</search-key-group>
	<search-key-group href="text/glossary.xhtml#bar">
		<match value="bar"/>
	</search-key-group>
	<search-key-group href="text/glossary.xhtml#ben">
		<match value="ben"/>
	</search-key-group>
	<search-key-group href="text/glossary.xhtml#bu">
		<match value="bu"/>
	</search-key-group>
	<search-key-group href="text/glossary.xhtml#bu-lot-moon-face">
		<match value="bu-lot"/>
	</search-key-group>
	<search-key-group href="text/glossary.xhtml#bu-lur-moon-city">
		<match value="bu-lur"/>
	</search-key-group>
	<search-key-group href="text/glossary.xhtml#dak">
		<match value="dak"/>
	</search-key-group>
	<search-key-group href="text/glossary.xhtml#dak-at-fat-tail">
		<match value="dak-at"/>
	</search-key-group>
	<search-key-group href="text/glossary.xhtml#dak-lot">
		<match value="dak-lot"/>
	</search-key-group>
	<search-key-group href="text/glossary.xhtml#dan">
		<match value="dan"/>
	</search-key-group>
	<search-key-group href="text/glossary.xhtml#den">
		<match value="den"/>
	</search-key-group>
	<search-key-group href="text/glossary.xhtml#don">
		<match value="don"/>
	</search-key-group>
	<search-key-group href="text/glossary.xhtml#dor">
		<match value="dor"/>
	</search-key-group>
	<search-key-group href="text/glossary.xhtml#dor-ul-otho-son-of-god">
		<match value="dor-ul-otho"/>
	</search-key-group>
	<search-key-group href="text/glossary.xhtml#e">
		<match value="e"/>
	</search-key-group>
	<search-key-group href="text/glossary.xhtml#ed">
		<match value="ed"/>
	</search-key-group>
	<search-key-group href="text/glossary.xhtml#el">
		<match value="el"/>
	</search-key-group>
	<search-key-group href="text/glossary.xhtml#en">
		<match value="en"/>
	</search-key-group>
	<search-key-group href="text/glossary.xhtml#enen">
		<match value="enen"/>
	</search-key-group>
	<search-key-group href="text/glossary.xhtml#es">
		<match value="es"/>
	</search-key-group>
	<search-key-group href="text/glossary.xhtml#es-sat-rough-skin">
		<match value="es-sat"/>
	</search-key-group>
	<search-key-group href="text/glossary.xhtml#et">
		<match value="et"/>
	</search-key-group>
	<search-key-group href="text/glossary.xhtml#fur">
		<match value="fur"/>
	</search-key-group>
	<search-key-group href="text/glossary.xhtml#ged">
		<match value="ged"/>
	</search-key-group>
	<search-key-group href="text/glossary.xhtml#go">
		<match value="go"/>
	</search-key-group>
	<search-key-group href="text/glossary.xhtml#gryf">
		<match value="gryf"/>
	</search-key-group>
	<search-key-group href="text/glossary.xhtml#gund">
		<match value="gund"/>
	</search-key-group>
	<search-key-group href="text/glossary.xhtml#guru">
		<match value="guru"/>
	</search-key-group>
	<search-key-group href="text/glossary.xhtml#het">
		<match value="het"/>
	</search-key-group>
	<search-key-group href="text/glossary.xhtml#ho">
		<match value="ho"/>
	</search-key-group>
	<search-key-group href="text/glossary.xhtml#ho-don">
		<match value="ho-don"/>
	</search-key-group>
	<search-key-group href="text/glossary.xhtml#id">
		<match value="id"/>
	</search-key-group>
	<search-key-group href="text/glossary.xhtml#id-an">
		<match value="id-an"/>
	</search-key-group>
	<search-key-group href="text/glossary.xhtml#in">
		<match value="in"/>
	</search-key-group>
	<search-key-group href="text/glossary.xhtml#in-sad">
		<match value="in-sad"/>
	</search-key-group>
	<search-key-group href="text/glossary.xhtml#in-tan">
		<match value="in-tan"/>
	</search-key-group>
	<search-key-group href="text/glossary.xhtml#ja">
		<match value="ja"/>
	</search-key-group>
	<search-key-group href="text/glossary.xhtml#jad">
		<match value="jad"/>
	</search-key-group>
	<search-key-group href="text/glossary.xhtml#jad-bal-lul">
		<match value="jad-bal-lul"/>
	</search-key-group>
	<search-key-group href="text/glossary.xhtml#jad-ben-lul">
		<match value="jad-ben-lul"/>
	</search-key-group>
	<search-key-group href="text/glossary.xhtml#jad-ben-otho">
		<match value="jad-ben-otho"/>
	</search-key-group>
	<search-key-group href="text/glossary.xhtml#jad-guru-don">
		<match value="jad-guru-don"/>
	</search-key-group>
	<search-key-group href="text/glossary.xhtml#jad-in-lul">
		<match value="jad-in-lul"/>
	</search-key-group>
	<search-key-group href="text/glossary.xhtml#ja-don-the-lion-man">
		<match value="ja-don"/>
	</search-key-group>
	<search-key-group href="text/glossary.xhtml#jad-pele-ul-jad-ben-otho">
		<match value="jad-pele-ul-jad-ben-otho"/>
	</search-key-group>
	<search-key-group href="text/glossary.xhtml#ja-lur-lion-city">
		<match value="ja-lur"/>
	</search-key-group>
	<search-key-group href="text/glossary.xhtml#jar">
		<match value="jar"/>
	</search-key-group>
	<search-key-group href="text/glossary.xhtml#jar-don">
		<match value="jar-don"/>
	</search-key-group>
	<search-key-group href="text/glossary.xhtml#jato">
		<match value="jato"/>
	</search-key-group>
	<search-key-group href="text/glossary.xhtml#ko">
		<match value="ko"/>
	</search-key-group>
	<search-key-group href="text/glossary.xhtml#kor">
		<match value="kor"/>
	</search-key-group>
	<search-key-group href="text/glossary.xhtml#kor-ul-gryf">
		<match value="kor-ul-gryf"/>
	</search-key-group>
	<search-key-group href="text/glossary.xhtml#kor-ul-ja">
		<match value="kor-ul-ja"/>
	</search-key-group>
	<search-key-group href="text/glossary.xhtml#kor-ul-lul">
		<match value="kor-ul-lul"/>
	</search-key-group>
	<search-key-group href="text/glossary.xhtml#ko-tan">
		<match value="ko-tan"/>
	</search-key-group>
	<search-key-group href="text/glossary.xhtml#lav">
		<match value="lav"/>
	</search-key-group>
	<search-key-group href="text/glossary.xhtml#lee">
		<match value="lee"/>
	</search-key-group>
	<search-key-group href="text/glossary.xhtml#lo">
		<match value="lo"/>
	</search-key-group>
	<search-key-group href="text/glossary.xhtml#lot">
		<match value="lot"/>
	</search-key-group>
	<search-key-group href="text/glossary.xhtml#lu">
		<match value="lu"/>
	</search-key-group>
	<search-key-group href="text/glossary.xhtml#lu-don-fierce-man">
		<match value="lu-don"/>
	</search-key-group>
	<search-key-group href="text/glossary.xhtml#lul">
		<match value="lul"/>
	</search-key-group>
	<search-key-group href="text/glossary.xhtml#lur">
		<match value="lur"/>
	</search-key-group>
	<search-key-group href="text/glossary.xhtml#ma">
		<match value="ma"/>
	</search-key-group>
	<search-key-group href="text/glossary.xhtml#mo">
		<match value="mo"/>
	</search-key-group>
	<search-key-group href="text/glossary.xhtml#mo-sar-short-nose">
		<match value="mo-sar"/>
	</search-key-group>
	<search-key-group href="text/glossary.xhtml#mu">
		<match value="mu"/>
	</search-key-group>
	<search-key-group href="text/glossary.xhtml#no">
		<match value="no"/>
	</search-key-group>
	<search-key-group href="text/glossary.xhtml#o">
		<match value="o"/>
	</search-key-group>
	<search-key-group href="text/glossary.xhtml#od">
		<match value="od"/>
	</search-key-group>
	<search-key-group href="text/glossary.xhtml#o-dan">
		<match value="o-dan"/>
	</search-key-group>
	<search-key-group href="text/glossary.xhtml#og">
		<match value="og"/>
	</search-key-group>
	<search-key-group href="text/glossary.xhtml#o-lo-a-like-star-light">
		<match value="o-lo-a"/>
	</search-key-group>
	<search-key-group href="text/glossary.xhtml#om">
		<match value="om"/>
	</search-key-group>
	<search-key-group href="text/glossary.xhtml#om-at-long-tail">
		<match value="om-at"/>
	</search-key-group>
	<search-key-group href="text/glossary.xhtml#on">
		<match value="on"/>
	</search-key-group>
	<search-key-group href="text/glossary.xhtml#otho">
		<match value="otho"/>
	</search-key-group>
	<search-key-group href="text/glossary.xhtml#pal">
		<match value="pal"/>
	</search-key-group>
	<search-key-group href="text/glossary.xhtml#pale-don-so-place-where-men-eat">
		<match value="pale-don-so"/>
	</search-key-group>
	<search-key-group href="text/glossary.xhtml#pal-ul-don-land-of-man">
		<match value="pal-ul-don"/>
	</search-key-group>
	<search-key-group href="text/glossary.xhtml#pal-ul-ja">
		<match value="pal-ul-ja"/>
	</search-key-group>
	<search-key-group href="text/glossary.xhtml#pan">
		<match value="pan"/>
	</search-key-group>
	<search-key-group href="text/glossary.xhtml#pan-at-lee">
		<match value="pan-at-lee"/>
	</search-key-group>
	<search-key-group href="text/glossary.xhtml#pan-sat-soft-skin">
		<match value="pan-sat"/>
	</search-key-group>
	<search-key-group href="text/glossary.xhtml#pastar">
		<match value="pastar"/>
	</search-key-group>
	<search-key-group href="text/glossary.xhtml#pastar-ul-ved">
		<match value="pastar-ul-ved"/>
	</search-key-group>
	<search-key-group href="text/glossary.xhtml#pele">
		<match value="pele"/>
	</search-key-group>
	<search-key-group href="text/glossary.xhtml#ro">
		<match value="ro"/>
	</search-key-group>
	<search-key-group href="text/glossary.xhtml#sad">
		<match value="sad"/>
	</search-key-group>
	<search-key-group href="text/glossary.xhtml#san">
		<match value="san"/>
	</search-key-group>
	<search-key-group href="text/glossary.xhtml#sar">
		<match value="sar"/>
	</search-key-group>
	<search-key-group href="text/glossary.xhtml#sat">
		<match value="sat"/>
	</search-key-group>
	<search-key-group href="text/glossary.xhtml#so">
		<match value="so"/>
	</search-key-group>
	<search-key-group href="text/glossary.xhtml#sod">
		<match value="sod"/>
	</search-key-group>
	<search-key-group href="text/glossary.xhtml#sog">
		<match value="sog"/>
	</search-key-group>
	<search-key-group href="text/glossary.xhtml#son">
		<match value="son"/>
	</search-key-group>
	<search-key-group href="text/glossary.xhtml#ta">
		<match value="ta"/>
	</search-key-group>
	<search-key-group href="text/glossary.xhtml#ta-den-tall-tree">
		<match value="ta-den"/>
	</search-key-group>
	<search-key-group href="text/glossary.xhtml#tan">
		<match value="tan"/>
	</search-key-group>
	<search-key-group href="text/glossary.xhtml#tarzan-jad-guru">
		<match value="tarzan-jad-guru"/>
	</search-key-group>
	<search-key-group href="text/glossary.xhtml#to">
		<match value="to"/>
	</search-key-group>
	<search-key-group href="text/glossary.xhtml#ton">
		<match value="ton"/>
	</search-key-group>
	<search-key-group href="text/glossary.xhtml#tor">
		<match value="tor"/>
	</search-key-group>
	<search-key-group href="text/glossary.xhtml#tor-o-don">
		<match value="tor-o-don"/>
	</search-key-group>
	<search-key-group href="text/glossary.xhtml#tu">
		<match value="tu"/>
	</search-key-group>
	<search-key-group href="text/glossary.xhtml#tu-lur-bright-city">
		<match value="tu-lur"/>
	</search-key-group>
	<search-key-group href="text/glossary.xhtml#ul">
		<match value="ul"/>
	</search-key-group>
	<search-key-group href="text/glossary.xhtml#un">
		<match value="un"/>
	</search-key-group>
	<search-key-group href="text/glossary.xhtml#ut">
		<match value="ut"/>
	</search-key-group>
	<search-key-group href="text/glossary.xhtml#ved">
		<match value="ved"/>
	</search-key-group>
	<search-key-group href="text/glossary.xhtml#waz">
		<match value="waz"/>
	</search-key-group>
	<search-key-group href="text/glossary.xhtml#waz-don">
		<match value="waz-don"/>
	</search-key-group>
	<search-key-group href="text/glossary.xhtml#waz-ho-don-black-white-men">
		<match value="waz-ho-don"/>
	</search-key-group>
	<search-key-group href="text/glossary.xhtml#xot">
		<match value="xot"/>
	</search-key-group>
	<search-key-group href="text/glossary.xhtml#yo">
		<match value="yo"/>
	</search-key-group>
	<search-key-group href="text/glossary.xhtml#za">
		<match value="za"/>
	</search-key-group>
</search-key-map>
